randel/__init__.py
randel/descriptive_statistics.py
randel/plotters.py
randel/estimators/__init__.py
randel/estimators/abstract.py
randel/estimators/chi_square.py
randel/estimators/classic.py
randel/estimators/covariance.py
randel/estimators/expectation.py
randel/models/__init__.py
randel/models/abstract.py
randel/models/canonic_expansion.py
randel/models/exact.py
randel/models/moving_sum.py
randel-0.1.dist-info/METADATA
randel-0.1.dist-info/WHEEL
randel-0.1.dist-info/top_level.txt
randel-0.1.dist-info/RECORD
